gens_input_data_tools/__init__.py
gens_input_data_tools/generate_cov_and_baf.py
gens_input_data_tools-2.0.0.dist-info/METADATA
gens_input_data_tools-2.0.0.dist-info/WHEEL
gens_input_data_tools-2.0.0.dist-info/entry_points.txt
gens_input_data_tools-2.0.0.dist-info/licenses/LICENSE.md
gens_input_data_tools-2.0.0.dist-info/RECORD
