Metadata-Version: 2.4
Name: gens_input_data_tools
Version: 2.0.0
Summary: Tools to generate Gens input data
Project-URL: Homepage, https://github.com/SMD-Bioinformatics-Lund/Prepare-Gens-input-data
Project-URL: Issues, https://github.com/SMD-Bioinformatics-Lund/Prepare-Gens-input-data/issues
Author-email: Jakob Willforss <jakob.willforss@skane.se>, Markus Johansson <markus.h.johansson@skane.se>
License-Expression: MIT
License-File: LICENSE.md
Classifier: Operating System :: OS Independent
Classifier: Programming Language :: Python :: 3
Requires-Python: >=3.12
